Metadata-Version: 2.1
Name: paci
Version: 1.10.5
Summary: Your friendly, lightweight and flexible package manager.
Home-page: https://github.com/tradebyte/paci
Author: Niklas Heer
Author-email: niklas.heer@tradebyte.com
License: MIT license
Download-URL: https://github.com/tradebyte/paci/archive/1.10.5.tar.gz
Keywords: cli,package-manager,install,linux,ubuntu,bash
Platform: UNKNOWN
Classifier: Intended Audience :: Developers
Classifier: License :: OSI Approved :: MIT License
Classifier: Topic :: System :: Software Distribution
Classifier: Natural Language :: English
Classifier: Operating System :: POSIX :: Linux
Classifier: Programming Language :: Python :: 3
Classifier: Programming Language :: Python :: 3.2
Classifier: Programming Language :: Python :: 3.3
Classifier: Programming Language :: Python :: 3.4
Classifier: Programming Language :: Python :: 3.5
Requires-Dist: docopt
Requires-Dist: better-exceptions
Requires-Dist: ruamel.yaml
Requires-Dist: json-traverse
Requires-Dist: clint
Requires-Dist: requests
Requires-Dist: jinja2
Requires-Dist: tinydb
Requires-Dist: tabulate
Requires-Dist: fuzzywuzzy
Requires-Dist: python-Levenshtein
